particlezoo/__init__.py
particlezoo-0.0.2.dist-info/LICENSE
particlezoo-0.0.2.dist-info/METADATA
particlezoo-0.0.2.dist-info/WHEEL
particlezoo-0.0.2.dist-info/top_level.txt
particlezoo-0.0.2.dist-info/RECORD
